cio/__init__.py
cio/api.py
cio/environment.py
cio/node.py
cio/backends/__init__.py
cio/backends/base.py
cio/backends/exceptions.py
cio/backends/locmem/__init__.py
cio/backends/locmem/backend.py
cio/backends/sqlite/__init__.py
cio/backends/sqlite/backend.py
cio/conf/__init__.py
cio/conf/default_settings.py
cio/conf/exceptions.py
cio/pipeline/__init__.py
cio/pipeline/buffer.py
cio/pipeline/handler.py
cio/pipeline/history.py
cio/pipeline/pipes/__init__.py
cio/pipeline/pipes/base.py
cio/pipeline/pipes/cache.py
cio/pipeline/pipes/meta.py
cio/pipeline/pipes/plugin.py
cio/pipeline/pipes/storage.py
cio/plugins/__init__.py
cio/plugins/base.py
cio/plugins/exceptions.py
cio/plugins/md.py
cio/plugins/txt.py
cio/utils/__init__.py
cio/utils/formatters.py
cio/utils/imports.py
cio/utils/thread.py
cio/utils/uri.py
tests/__init__.py
tests/test_api.py
tests/test_app.py
tests/test_cache.py
tests/test_plugins.py
tests/test_storage.py
tests/test_utils.py
content_io-1.3b2.dist-info/AUTHORS
content_io-1.3b2.dist-info/LICENSE
content_io-1.3b2.dist-info/METADATA
content_io-1.3b2.dist-info/WHEEL
content_io-1.3b2.dist-info/top_level.txt
content_io-1.3b2.dist-info/RECORD
