Metadata-Version: 2.1
Name: content-io
Version: 1.3b2
Summary: Send content through a highly configurable pipeline including cache, plugin and storage pipes
Home-page: https://github.com/5monkeys/content-io
Author: Jonas Lundberg
Author-email: jonas@5monkeys.se
License: BSD
Download-URL: https://github.com/5monkeys/content-io/tarball/1.3b2
Keywords: cms,content,management,pipeline,plugin,backend,cache,storage
Platform: UNKNOWN
Classifier: Environment :: Web Environment
Classifier: Natural Language :: English
Classifier: Intended Audience :: Developers
Classifier: License :: OSI Approved :: BSD License
Classifier: Operating System :: OS Independent
Classifier: Programming Language :: Python
Classifier: Programming Language :: Python :: 2
Classifier: Programming Language :: Python :: 2.7
Classifier: Programming Language :: Python :: 3
Classifier: Programming Language :: Python :: 3.5
Classifier: Programming Language :: Python :: 3.6
Classifier: Topic :: Internet :: WWW/HTTP :: Dynamic Content
Classifier: Topic :: Software Development :: Libraries :: Python Modules
Requires-Dist: six
Provides-Extra: tests
Requires-Dist: coverage ; extra == 'tests'
Requires-Dist: Markdown ; extra == 'tests'
